Metadata-Version: 1.0
Name: names-wiktormalinowski
Version: 0.0.2
Summary: Super useful library
Home-page: UNKNOWN
Author: Wiktor Malinowski
Author-email: abc@gmail.com
License: UNKNOWN
Platform: UNKNOWN
